filetools/__init__.py
filetools/__main__.py
filetools/class_error.py
filetools/filetools_utilities.py
effcorp_filetools-1.3.1.dist-info/LICENSE
effcorp_filetools-1.3.1.dist-info/METADATA
effcorp_filetools-1.3.1.dist-info/WHEEL
effcorp_filetools-1.3.1.dist-info/entry_points.txt
effcorp_filetools-1.3.1.dist-info/top_level.txt
effcorp_filetools-1.3.1.dist-info/RECORD
