Metadata-Version: 2.1
Name: effcorp-filetools
Version: 1.3.1
Summary: A python module to simplify various files related work in your day to day office or personal work
Home-page: https://github.com/EFFICIENTCORPORATES/effcorp-filetools
Author: Efficient_Corporates
Author-email: efficientcorporates.info@gmail.com
License: GNU GP License
Classifier: License :: OSI Approved :: GNU General Public License v3 or later (GPLv3+)
Classifier: Programming Language :: Python :: 3.6
Classifier: Programming Language :: Python :: 3.7
Classifier: Programming Language :: Python :: 3.8
License-File: LICENSE
Requires-Dist: pandas
Requires-Dist: numpy
Requires-Dist: openpyxl
Requires-Dist: XlsxWriter
Requires-Dist: reportlab
Requires-Dist: PyPDF2
Requires-Dist: pdfminer
Requires-Dist: datetime
Requires-Dist: tabula
Requires-Dist: tabulate
Requires-Dist: PyPDF4
Requires-Dist: fpdf
